weblogtools/__init__.py
weblogtools/admin.py
weblogtools/apps.py
weblogtools/biz.py
weblogtools/models.py
weblogtools/signals.py
weblogtools/tests.py
weblogtools/views.py
weblogtools/migrations/0001_initial.py
weblogtools/migrations/__init__.py
weblogtools/templates/weblogtools/change_form.html
django_weblogtools-0.1.3.dist-info/LICENSE
django_weblogtools-0.1.3.dist-info/METADATA
django_weblogtools-0.1.3.dist-info/WHEEL
django_weblogtools-0.1.3.dist-info/top_level.txt
django_weblogtools-0.1.3.dist-info/RECORD
